setup.py
string_to_hex_color/__init__.py
string_to_hex_color.egg-info/PKG-INFO
string_to_hex_color.egg-info/SOURCES.txt
string_to_hex_color.egg-info/dependency_links.txt
string_to_hex_color.egg-info/not-zip-safe
string_to_hex_color.egg-info/top_level.txt