Metadata-Version: 1.0
Name: string-to-hex-color
Version: 0.1
Summary: convert any string to a hex based color
Home-page: http://github.com/micahwalter/string_to_hex_color
Author: Micah Walter
Author-email: micah@micahwalter.com
License: MIT
Platform: UNKNOWN
